setup.py
CliTools.egg-info/PKG-INFO
CliTools.egg-info/SOURCES.txt
CliTools.egg-info/dependency_links.txt
CliTools.egg-info/top_level.txt
clitools/__init__.py