Metadata-Version: 1.1
Name: CliTools
Version: 0.2
Summary: Utilities for building CLI scripts in Python
Home-page: http://rshk.github.io/clitools
Author: Samuele Santi
Author-email: samuele@samuelesanti.com
License: BSD License
Platform: UNKNOWN
Classifier: License :: OSI Approved :: BSD License
Classifier: Development Status :: 3 - Alpha
Classifier: Programming Language :: Python :: 2
Classifier: Programming Language :: Python :: 2.6
Classifier: Programming Language :: Python :: 2.7
Classifier: Programming Language :: Python :: 3.2
Classifier: Programming Language :: Python :: 3.3
Classifier: Programming Language :: Python :: Implementation :: PyPy
